ollamawebui.py
ollamawebui-3.0.0.dist-info/METADATA
ollamawebui-3.0.0.dist-info/WHEEL
ollamawebui-3.0.0.dist-info/entry_points.txt
ollamawebui-3.0.0.dist-info/top_level.txt
ollamawebui-3.0.0.dist-info/RECORD
