Metadata-Version: 2.2
Name: ollamawebui
Version: 3.0.0
Summary: OllamaWebUI-A Simple Flask WebUI, You Can Chat With Ollama On Web|Flask聊天界面，可以自定义设置Ollama Api（python学霸公众号）
Author: Python学霸
Author-email: python@xueba.com
Requires-Dist: Flask
Requires-Dist: requests
Requires-Dist: beautifulsoup4
Dynamic: author
Dynamic: author-email
Dynamic: description
Dynamic: description-content-type
Dynamic: requires-dist
Dynamic: summary
